[{"page":1,"pages":1,"per_page":"10000","total":27},[{"indicator":{"id":"3.1.3_HYDRO.CONSUM","value":"Hydro energy consumption (TJ)"},"country":{"id":"AF","value":"Afghanistan"},"value":null,"decimal":"0","date":"Period 2010-2012"},{"indicator":{"id":"3.1.3_HYDRO.CONSUM","value":"Hydro energy consumption (TJ)"},"country":{"id":"AF","value":"Afghanistan"},"value":null,"decimal":"0","date":"Period 2000-2010"},{"indicator":{"id":"3.1.3_HYDRO.CONSUM","value":"Hydro energy consumption (TJ)"},"country":{"id":"AF","value":"Afghanistan"},"value":null,"decimal":"0","date":"Period 1990-2012"},{"indicator":{"id":"3.1.3_HYDRO.CONSUM","value":"Hydro energy consumption (TJ)"},"country":{"id":"AF","value":"Afghanistan"},"value":null,"decimal":"0","date":"Period 1990-2000"},{"indicator":{"id":"3.1.3_HYDRO.CONSUM","value":"Hydro energy consumption (TJ)"},"country":{"id":"AF","value":"Afghanistan"},"value":"7769.02852570977","decimal":"0","date":"2012"},{"indicator":{"id":"3.1.3_HYDRO.CONSUM","value":"Hydro energy consumption (TJ)"},"country":{"id":"AF","value":"Afghanistan"},"value":"6829.97014925373","decimal":"0","date":"2011"},{"indicator":{"id":"3.1.3_HYDRO.CONSUM","value":"Hydro energy consumption (TJ)"},"country":{"id":"AF","value":"Afghanistan"},"value":"7429.23766816144","decimal":"0","date":"2010"},{"indicator":{"id":"3.1.3_HYDRO.CONSUM","value":"Hydro energy consumption (TJ)"},"country":{"id":"AF","value":"Afghanistan"},"value":"5021.37232845894","decimal":"0","date":"2009"},{"indicator":{"id":"3.1.3_HYDRO.CONSUM","value":"Hydro energy consumption (TJ)"},"country":{"id":"AF","value":"Afghanistan"},"value":"3707.36040609137","decimal":"0","date":"2008"},{"indicator":{"id":"3.1.3_HYDRO.CONSUM","value":"Hydro energy consumption (TJ)"},"country":{"id":"AF","value":"Afghanistan"},"value":"3888","decimal":"0","date":"2007"},{"indicator":{"id":"3.1.3_HYDRO.CONSUM","value":"Hydro energy consumption (TJ)"},"country":{"id":"AF","value":"Afghanistan"},"value":"3158.53669222344","decimal":"0","date":"2006"},{"indicator":{"id":"3.1.3_HYDRO.CONSUM","value":"Hydro energy consumption (TJ)"},"country":{"id":"AF","value":"Afghanistan"},"value":"2292.95364238411","decimal":"0","date":"2005"},{"indicator":{"id":"3.1.3_HYDRO.CONSUM","value":"Hydro energy consumption (TJ)"},"country":{"id":"AF","value":"Afghanistan"},"value":"2242.61538461538","decimal":"0","date":"2004"},{"indicator":{"id":"3.1.3_HYDRO.CONSUM","value":"Hydro energy consumption (TJ)"},"country":{"id":"AF","value":"Afghanistan"},"value":"2104.87131147541","decimal":"0","date":"2003"},{"indicator":{"id":"3.1.3_HYDRO.CONSUM","value":"Hydro energy consumption (TJ)"},"country":{"id":"AF","value":"Afghanistan"},"value":"1855.7895319856","decimal":"0","date":"2002"},{"indicator":{"id":"3.1.3_HYDRO.CONSUM","value":"Hydro energy consumption (TJ)"},"country":{"id":"AF","value":"Afghanistan"},"value":"1625.15178700622","decimal":"0","date":"2001"},{"indicator":{"id":"3.1.3_HYDRO.CONSUM","value":"Hydro energy consumption (TJ)"},"country":{"id":"AF","value":"Afghanistan"},"value":"1665.6577577432","decimal":"0","date":"2000"},{"indicator":{"id":"3.1.3_HYDRO.CONSUM","value":"Hydro energy consumption (TJ)"},"country":{"id":"AF","value":"Afghanistan"},"value":"1629.56496350365","decimal":"0","date":"1999"},{"indicator":{"id":"3.1.3_HYDRO.CONSUM","value":"Hydro energy consumption (TJ)"},"country":{"id":"AF","value":"Afghanistan"},"value":"1591.74135338346","decimal":"0","date":"1998"},{"indicator":{"id":"3.1.3_HYDRO.CONSUM","value":"Hydro energy consumption (TJ)"},"country":{"id":"AF","value":"Afghanistan"},"value":"1571.4","decimal":"0","date":"1997"},{"indicator":{"id":"3.1.3_HYDRO.CONSUM","value":"Hydro energy consumption (TJ)"},"country":{"id":"AF","value":"Afghanistan"},"value":"1560.53333333333","decimal":"0","date":"1996"},{"indicator":{"id":"3.1.3_HYDRO.CONSUM","value":"Hydro energy consumption (TJ)"},"country":{"id":"AF","value":"Afghanistan"},"value":"1555.81866666667","decimal":"0","date":"1995"},{"indicator":{"id":"3.1.3_HYDRO.CONSUM","value":"Hydro energy consumption (TJ)"},"country":{"id":"AF","value":"Afghanistan"},"value":"1582.9519650655","decimal":"0","date":"1994"},{"indicator":{"id":"3.1.3_HYDRO.CONSUM","value":"Hydro energy consumption (TJ)"},"country":{"id":"AF","value":"Afghanistan"},"value":"1599.28057553957","decimal":"0","date":"1993"},{"indicator":{"id":"3.1.3_HYDRO.CONSUM","value":"Hydro energy consumption (TJ)"},"country":{"id":"AF","value":"Afghanistan"},"value":"719.651778093883","decimal":"0","date":"1992"},{"indicator":{"id":"3.1.3_HYDRO.CONSUM","value":"Hydro energy consumption (TJ)"},"country":{"id":"AF","value":"Afghanistan"},"value":"881.024630541872","decimal":"0","date":"1991"},{"indicator":{"id":"3.1.3_HYDRO.CONSUM","value":"Hydro energy consumption (TJ)"},"country":{"id":"AF","value":"Afghanistan"},"value":"985.072340425532","decimal":"0","date":"1990"}]]