[{"page":1,"pages":1,"per_page":"10000","total":27},[{"indicator":{"id":"3.1.3_HYDRO.CONSUM","value":"Hydro energy consumption (TJ)"},"country":{"id":"CL","value":"Chile"},"value":null,"decimal":"0","date":"Period 2010-2012"},{"indicator":{"id":"3.1.3_HYDRO.CONSUM","value":"Hydro energy consumption (TJ)"},"country":{"id":"CL","value":"Chile"},"value":null,"decimal":"0","date":"Period 2000-2010"},{"indicator":{"id":"3.1.3_HYDRO.CONSUM","value":"Hydro energy consumption (TJ)"},"country":{"id":"CL","value":"Chile"},"value":null,"decimal":"0","date":"Period 1990-2012"},{"indicator":{"id":"3.1.3_HYDRO.CONSUM","value":"Hydro energy consumption (TJ)"},"country":{"id":"CL","value":"Chile"},"value":null,"decimal":"0","date":"Period 1990-2000"},{"indicator":{"id":"3.1.3_HYDRO.CONSUM","value":"Hydro energy consumption (TJ)"},"country":{"id":"CL","value":"Chile"},"value":"64744.1748184255","decimal":"0","date":"2012"},{"indicator":{"id":"3.1.3_HYDRO.CONSUM","value":"Hydro energy consumption (TJ)"},"country":{"id":"CL","value":"Chile"},"value":"66688.8572224674","decimal":"0","date":"2011"},{"indicator":{"id":"3.1.3_HYDRO.CONSUM","value":"Hydro energy consumption (TJ)"},"country":{"id":"CL","value":"Chile"},"value":"70825.2445244399","decimal":"0","date":"2010"},{"indicator":{"id":"3.1.3_HYDRO.CONSUM","value":"Hydro energy consumption (TJ)"},"country":{"id":"CL","value":"Chile"},"value":"81050.1011718982","decimal":"0","date":"2009"},{"indicator":{"id":"3.1.3_HYDRO.CONSUM","value":"Hydro energy consumption (TJ)"},"country":{"id":"CL","value":"Chile"},"value":"78070.268821352","decimal":"0","date":"2008"},{"indicator":{"id":"3.1.3_HYDRO.CONSUM","value":"Hydro energy consumption (TJ)"},"country":{"id":"CL","value":"Chile"},"value":"75486.9049684664","decimal":"0","date":"2007"},{"indicator":{"id":"3.1.3_HYDRO.CONSUM","value":"Hydro energy consumption (TJ)"},"country":{"id":"CL","value":"Chile"},"value":"96326.9070404917","decimal":"0","date":"2006"},{"indicator":{"id":"3.1.3_HYDRO.CONSUM","value":"Hydro energy consumption (TJ)"},"country":{"id":"CL","value":"Chile"},"value":"87781.4820655819","decimal":"0","date":"2005"},{"indicator":{"id":"3.1.3_HYDRO.CONSUM","value":"Hydro energy consumption (TJ)"},"country":{"id":"CL","value":"Chile"},"value":"72721.9947295344","decimal":"0","date":"2004"},{"indicator":{"id":"3.1.3_HYDRO.CONSUM","value":"Hydro energy consumption (TJ)"},"country":{"id":"CL","value":"Chile"},"value":"74102.5076414188","decimal":"0","date":"2003"},{"indicator":{"id":"3.1.3_HYDRO.CONSUM","value":"Hydro energy consumption (TJ)"},"country":{"id":"CL","value":"Chile"},"value":"75169.7163437979","decimal":"0","date":"2002"},{"indicator":{"id":"3.1.3_HYDRO.CONSUM","value":"Hydro energy consumption (TJ)"},"country":{"id":"CL","value":"Chile"},"value":"70277.6597312549","decimal":"0","date":"2001"},{"indicator":{"id":"3.1.3_HYDRO.CONSUM","value":"Hydro energy consumption (TJ)"},"country":{"id":"CL","value":"Chile"},"value":"61136.8123738709","decimal":"0","date":"2000"},{"indicator":{"id":"3.1.3_HYDRO.CONSUM","value":"Hydro energy consumption (TJ)"},"country":{"id":"CL","value":"Chile"},"value":"44308.4727976035","decimal":"0","date":"1999"},{"indicator":{"id":"3.1.3_HYDRO.CONSUM","value":"Hydro energy consumption (TJ)"},"country":{"id":"CL","value":"Chile"},"value":"50044.493233828","decimal":"0","date":"1998"},{"indicator":{"id":"3.1.3_HYDRO.CONSUM","value":"Hydro energy consumption (TJ)"},"country":{"id":"CL","value":"Chile"},"value":"60125.2393945401","decimal":"0","date":"1997"},{"indicator":{"id":"3.1.3_HYDRO.CONSUM","value":"Hydro energy consumption (TJ)"},"country":{"id":"CL","value":"Chile"},"value":"53166.4775147236","decimal":"0","date":"1996"},{"indicator":{"id":"3.1.3_HYDRO.CONSUM","value":"Hydro energy consumption (TJ)"},"country":{"id":"CL","value":"Chile"},"value":"57230.0313383523","decimal":"0","date":"1995"},{"indicator":{"id":"3.1.3_HYDRO.CONSUM","value":"Hydro energy consumption (TJ)"},"country":{"id":"CL","value":"Chile"},"value":"52384.6640653559","decimal":"0","date":"1994"},{"indicator":{"id":"3.1.3_HYDRO.CONSUM","value":"Hydro energy consumption (TJ)"},"country":{"id":"CL","value":"Chile"},"value":"54514.9713902429","decimal":"0","date":"1993"},{"indicator":{"id":"3.1.3_HYDRO.CONSUM","value":"Hydro energy consumption (TJ)"},"country":{"id":"CL","value":"Chile"},"value":"52087.9984796315","decimal":"0","date":"1992"},{"indicator":{"id":"3.1.3_HYDRO.CONSUM","value":"Hydro energy consumption (TJ)"},"country":{"id":"CL","value":"Chile"},"value":"40166.8329372276","decimal":"0","date":"1991"},{"indicator":{"id":"3.1.3_HYDRO.CONSUM","value":"Hydro energy consumption (TJ)"},"country":{"id":"CL","value":"Chile"},"value":"27102.0296276943","decimal":"0","date":"1990"}]]