[{"page":1,"pages":1,"per_page":"10000","total":27},[{"indicator":{"id":"8.1.2_FINAL.ENERGY.INTENSITY","value":"Energy intensity level of final energy (MJ\/2011 USD PPP)"},"country":{"id":"CN","value":"China"},"value":null,"decimal":"2","date":"Period 2010-2012"},{"indicator":{"id":"8.1.2_FINAL.ENERGY.INTENSITY","value":"Energy intensity level of final energy (MJ\/2011 USD PPP)"},"country":{"id":"CN","value":"China"},"value":null,"decimal":"2","date":"Period 2000-2010"},{"indicator":{"id":"8.1.2_FINAL.ENERGY.INTENSITY","value":"Energy intensity level of final energy (MJ\/2011 USD PPP)"},"country":{"id":"CN","value":"China"},"value":null,"decimal":"2","date":"Period 1990-2012"},{"indicator":{"id":"8.1.2_FINAL.ENERGY.INTENSITY","value":"Energy intensity level of final energy (MJ\/2011 USD PPP)"},"country":{"id":"CN","value":"China"},"value":null,"decimal":"2","date":"Period 1990-2000"},{"indicator":{"id":"8.1.2_FINAL.ENERGY.INTENSITY","value":"Energy intensity level of final energy (MJ\/2011 USD PPP)"},"country":{"id":"CN","value":"China"},"value":"4.51233521135663","decimal":"2","date":"2012"},{"indicator":{"id":"8.1.2_FINAL.ENERGY.INTENSITY","value":"Energy intensity level of final energy (MJ\/2011 USD PPP)"},"country":{"id":"CN","value":"China"},"value":"4.67578837811476","decimal":"2","date":"2011"},{"indicator":{"id":"8.1.2_FINAL.ENERGY.INTENSITY","value":"Energy intensity level of final energy (MJ\/2011 USD PPP)"},"country":{"id":"CN","value":"China"},"value":"4.76954162246289","decimal":"2","date":"2010"},{"indicator":{"id":"8.1.2_FINAL.ENERGY.INTENSITY","value":"Energy intensity level of final energy (MJ\/2011 USD PPP)"},"country":{"id":"CN","value":"China"},"value":"4.92016093239598","decimal":"2","date":"2009"},{"indicator":{"id":"8.1.2_FINAL.ENERGY.INTENSITY","value":"Energy intensity level of final energy (MJ\/2011 USD PPP)"},"country":{"id":"CN","value":"China"},"value":"5.17330231374178","decimal":"2","date":"2008"},{"indicator":{"id":"8.1.2_FINAL.ENERGY.INTENSITY","value":"Energy intensity level of final energy (MJ\/2011 USD PPP)"},"country":{"id":"CN","value":"China"},"value":"5.50033404598719","decimal":"2","date":"2007"},{"indicator":{"id":"8.1.2_FINAL.ENERGY.INTENSITY","value":"Energy intensity level of final energy (MJ\/2011 USD PPP)"},"country":{"id":"CN","value":"China"},"value":"5.8971494927346","decimal":"2","date":"2006"},{"indicator":{"id":"8.1.2_FINAL.ENERGY.INTENSITY","value":"Energy intensity level of final energy (MJ\/2011 USD PPP)"},"country":{"id":"CN","value":"China"},"value":"6.19371320116111","decimal":"2","date":"2005"},{"indicator":{"id":"8.1.2_FINAL.ENERGY.INTENSITY","value":"Energy intensity level of final energy (MJ\/2011 USD PPP)"},"country":{"id":"CN","value":"China"},"value":"6.32188269841886","decimal":"2","date":"2004"},{"indicator":{"id":"8.1.2_FINAL.ENERGY.INTENSITY","value":"Energy intensity level of final energy (MJ\/2011 USD PPP)"},"country":{"id":"CN","value":"China"},"value":"6.0978846936162","decimal":"2","date":"2003"},{"indicator":{"id":"8.1.2_FINAL.ENERGY.INTENSITY","value":"Energy intensity level of final energy (MJ\/2011 USD PPP)"},"country":{"id":"CN","value":"China"},"value":"6.10291125490596","decimal":"2","date":"2002"},{"indicator":{"id":"8.1.2_FINAL.ENERGY.INTENSITY","value":"Energy intensity level of final energy (MJ\/2011 USD PPP)"},"country":{"id":"CN","value":"China"},"value":"6.47806177645928","decimal":"2","date":"2001"},{"indicator":{"id":"8.1.2_FINAL.ENERGY.INTENSITY","value":"Energy intensity level of final energy (MJ\/2011 USD PPP)"},"country":{"id":"CN","value":"China"},"value":"6.92404040553963","decimal":"2","date":"2000"},{"indicator":{"id":"8.1.2_FINAL.ENERGY.INTENSITY","value":"Energy intensity level of final energy (MJ\/2011 USD PPP)"},"country":{"id":"CN","value":"China"},"value":"7.13246061744325","decimal":"2","date":"1999"},{"indicator":{"id":"8.1.2_FINAL.ENERGY.INTENSITY","value":"Energy intensity level of final energy (MJ\/2011 USD PPP)"},"country":{"id":"CN","value":"China"},"value":"7.90498353076896","decimal":"2","date":"1998"},{"indicator":{"id":"8.1.2_FINAL.ENERGY.INTENSITY","value":"Energy intensity level of final energy (MJ\/2011 USD PPP)"},"country":{"id":"CN","value":"China"},"value":"8.55164657170696","decimal":"2","date":"1997"},{"indicator":{"id":"8.1.2_FINAL.ENERGY.INTENSITY","value":"Energy intensity level of final energy (MJ\/2011 USD PPP)"},"country":{"id":"CN","value":"China"},"value":"9.42987182129667","decimal":"2","date":"1996"},{"indicator":{"id":"8.1.2_FINAL.ENERGY.INTENSITY","value":"Energy intensity level of final energy (MJ\/2011 USD PPP)"},"country":{"id":"CN","value":"China"},"value":"10.6329293091142","decimal":"2","date":"1995"},{"indicator":{"id":"8.1.2_FINAL.ENERGY.INTENSITY","value":"Energy intensity level of final energy (MJ\/2011 USD PPP)"},"country":{"id":"CN","value":"China"},"value":"11.3240835349228","decimal":"2","date":"1994"},{"indicator":{"id":"8.1.2_FINAL.ENERGY.INTENSITY","value":"Energy intensity level of final energy (MJ\/2011 USD PPP)"},"country":{"id":"CN","value":"China"},"value":"12.6345031499403","decimal":"2","date":"1993"},{"indicator":{"id":"8.1.2_FINAL.ENERGY.INTENSITY","value":"Energy intensity level of final energy (MJ\/2011 USD PPP)"},"country":{"id":"CN","value":"China"},"value":"13.7267088320554","decimal":"2","date":"1992"},{"indicator":{"id":"8.1.2_FINAL.ENERGY.INTENSITY","value":"Energy intensity level of final energy (MJ\/2011 USD PPP)"},"country":{"id":"CN","value":"China"},"value":"14.7116650657913","decimal":"2","date":"1991"},{"indicator":{"id":"8.1.2_FINAL.ENERGY.INTENSITY","value":"Energy intensity level of final energy (MJ\/2011 USD PPP)"},"country":{"id":"CN","value":"China"},"value":"14.7466929381925","decimal":"2","date":"1990"}]]