[{"page":1,"pages":1,"per_page":"10000","total":27},[{"indicator":{"id":"3.1.9_BIOGAS.CONSUM","value":"Biogas consumption (TJ)"},"country":{"id":"DE","value":"Germany"},"value":null,"decimal":"0","date":"Period 2010-2012"},{"indicator":{"id":"3.1.9_BIOGAS.CONSUM","value":"Biogas consumption (TJ)"},"country":{"id":"DE","value":"Germany"},"value":null,"decimal":"0","date":"Period 2000-2010"},{"indicator":{"id":"3.1.9_BIOGAS.CONSUM","value":"Biogas consumption (TJ)"},"country":{"id":"DE","value":"Germany"},"value":null,"decimal":"0","date":"Period 1990-2012"},{"indicator":{"id":"3.1.9_BIOGAS.CONSUM","value":"Biogas consumption (TJ)"},"country":{"id":"DE","value":"Germany"},"value":null,"decimal":"0","date":"Period 1990-2000"},{"indicator":{"id":"3.1.9_BIOGAS.CONSUM","value":"Biogas consumption (TJ)"},"country":{"id":"DE","value":"Germany"},"value":"129060.921811822","decimal":"0","date":"2012"},{"indicator":{"id":"3.1.9_BIOGAS.CONSUM","value":"Biogas consumption (TJ)"},"country":{"id":"DE","value":"Germany"},"value":"109193.391731567","decimal":"0","date":"2011"},{"indicator":{"id":"3.1.9_BIOGAS.CONSUM","value":"Biogas consumption (TJ)"},"country":{"id":"DE","value":"Germany"},"value":"89351.3400074065","decimal":"0","date":"2010"},{"indicator":{"id":"3.1.9_BIOGAS.CONSUM","value":"Biogas consumption (TJ)"},"country":{"id":"DE","value":"Germany"},"value":"71513.0405916028","decimal":"0","date":"2009"},{"indicator":{"id":"3.1.9_BIOGAS.CONSUM","value":"Biogas consumption (TJ)"},"country":{"id":"DE","value":"Germany"},"value":"58362.1403239793","decimal":"0","date":"2008"},{"indicator":{"id":"3.1.9_BIOGAS.CONSUM","value":"Biogas consumption (TJ)"},"country":{"id":"DE","value":"Germany"},"value":"51543.9817238421","decimal":"0","date":"2007"},{"indicator":{"id":"3.1.9_BIOGAS.CONSUM","value":"Biogas consumption (TJ)"},"country":{"id":"DE","value":"Germany"},"value":"28378.6274099334","decimal":"0","date":"2006"},{"indicator":{"id":"3.1.9_BIOGAS.CONSUM","value":"Biogas consumption (TJ)"},"country":{"id":"DE","value":"Germany"},"value":"22509.83917826","decimal":"0","date":"2005"},{"indicator":{"id":"3.1.9_BIOGAS.CONSUM","value":"Biogas consumption (TJ)"},"country":{"id":"DE","value":"Germany"},"value":"18219.4638810889","decimal":"0","date":"2004"},{"indicator":{"id":"3.1.9_BIOGAS.CONSUM","value":"Biogas consumption (TJ)"},"country":{"id":"DE","value":"Germany"},"value":"17717.8555079749","decimal":"0","date":"2003"},{"indicator":{"id":"3.1.9_BIOGAS.CONSUM","value":"Biogas consumption (TJ)"},"country":{"id":"DE","value":"Germany"},"value":"26565.1795066012","decimal":"0","date":"2002"},{"indicator":{"id":"3.1.9_BIOGAS.CONSUM","value":"Biogas consumption (TJ)"},"country":{"id":"DE","value":"Germany"},"value":"18990.0049639905","decimal":"0","date":"2001"},{"indicator":{"id":"3.1.9_BIOGAS.CONSUM","value":"Biogas consumption (TJ)"},"country":{"id":"DE","value":"Germany"},"value":"10104.8540425565","decimal":"0","date":"2000"},{"indicator":{"id":"3.1.9_BIOGAS.CONSUM","value":"Biogas consumption (TJ)"},"country":{"id":"DE","value":"Germany"},"value":"7763.32521669732","decimal":"0","date":"1999"},{"indicator":{"id":"3.1.9_BIOGAS.CONSUM","value":"Biogas consumption (TJ)"},"country":{"id":"DE","value":"Germany"},"value":"6959.75011380461","decimal":"0","date":"1998"},{"indicator":{"id":"3.1.9_BIOGAS.CONSUM","value":"Biogas consumption (TJ)"},"country":{"id":"DE","value":"Germany"},"value":"5878.70630415406","decimal":"0","date":"1997"},{"indicator":{"id":"3.1.9_BIOGAS.CONSUM","value":"Biogas consumption (TJ)"},"country":{"id":"DE","value":"Germany"},"value":"5386.04759175083","decimal":"0","date":"1996"},{"indicator":{"id":"3.1.9_BIOGAS.CONSUM","value":"Biogas consumption (TJ)"},"country":{"id":"DE","value":"Germany"},"value":"5088.05695852483","decimal":"0","date":"1995"},{"indicator":{"id":"3.1.9_BIOGAS.CONSUM","value":"Biogas consumption (TJ)"},"country":{"id":"DE","value":"Germany"},"value":"4291.81431540997","decimal":"0","date":"1994"},{"indicator":{"id":"3.1.9_BIOGAS.CONSUM","value":"Biogas consumption (TJ)"},"country":{"id":"DE","value":"Germany"},"value":"4257.65960189866","decimal":"0","date":"1993"},{"indicator":{"id":"3.1.9_BIOGAS.CONSUM","value":"Biogas consumption (TJ)"},"country":{"id":"DE","value":"Germany"},"value":"4123.67785672484","decimal":"0","date":"1992"},{"indicator":{"id":"3.1.9_BIOGAS.CONSUM","value":"Biogas consumption (TJ)"},"country":{"id":"DE","value":"Germany"},"value":"7070.24948821207","decimal":"0","date":"1991"},{"indicator":{"id":"3.1.9_BIOGAS.CONSUM","value":"Biogas consumption (TJ)"},"country":{"id":"DE","value":"Germany"},"value":"6609.68523466648","decimal":"0","date":"1990"}]]