[{"page":1,"pages":1,"per_page":"10000","total":27},[{"indicator":{"id":"8.1.2_FINAL.ENERGY.INTENSITY","value":"Energy intensity level of final energy (MJ\/2011 USD PPP)"},"country":{"id":"HK","value":"Hong Kong SAR, China"},"value":null,"decimal":"2","date":"Period 2010-2012"},{"indicator":{"id":"8.1.2_FINAL.ENERGY.INTENSITY","value":"Energy intensity level of final energy (MJ\/2011 USD PPP)"},"country":{"id":"HK","value":"Hong Kong SAR, China"},"value":null,"decimal":"2","date":"Period 2000-2010"},{"indicator":{"id":"8.1.2_FINAL.ENERGY.INTENSITY","value":"Energy intensity level of final energy (MJ\/2011 USD PPP)"},"country":{"id":"HK","value":"Hong Kong SAR, China"},"value":null,"decimal":"2","date":"Period 1990-2012"},{"indicator":{"id":"8.1.2_FINAL.ENERGY.INTENSITY","value":"Energy intensity level of final energy (MJ\/2011 USD PPP)"},"country":{"id":"HK","value":"Hong Kong SAR, China"},"value":null,"decimal":"2","date":"Period 1990-2000"},{"indicator":{"id":"8.1.2_FINAL.ENERGY.INTENSITY","value":"Energy intensity level of final energy (MJ\/2011 USD PPP)"},"country":{"id":"HK","value":"Hong Kong SAR, China"},"value":"0.993347134607528","decimal":"2","date":"2012"},{"indicator":{"id":"8.1.2_FINAL.ENERGY.INTENSITY","value":"Energy intensity level of final energy (MJ\/2011 USD PPP)"},"country":{"id":"HK","value":"Hong Kong SAR, China"},"value":"1.00011926058993","decimal":"2","date":"2011"},{"indicator":{"id":"8.1.2_FINAL.ENERGY.INTENSITY","value":"Energy intensity level of final energy (MJ\/2011 USD PPP)"},"country":{"id":"HK","value":"Hong Kong SAR, China"},"value":"1.00352165014091","decimal":"2","date":"2010"},{"indicator":{"id":"8.1.2_FINAL.ENERGY.INTENSITY","value":"Energy intensity level of final energy (MJ\/2011 USD PPP)"},"country":{"id":"HK","value":"Hong Kong SAR, China"},"value":"1.15176949419473","decimal":"2","date":"2009"},{"indicator":{"id":"8.1.2_FINAL.ENERGY.INTENSITY","value":"Energy intensity level of final energy (MJ\/2011 USD PPP)"},"country":{"id":"HK","value":"Hong Kong SAR, China"},"value":"1.01906965407241","decimal":"2","date":"2008"},{"indicator":{"id":"8.1.2_FINAL.ENERGY.INTENSITY","value":"Energy intensity level of final energy (MJ\/2011 USD PPP)"},"country":{"id":"HK","value":"Hong Kong SAR, China"},"value":"1.02821068810342","decimal":"2","date":"2007"},{"indicator":{"id":"8.1.2_FINAL.ENERGY.INTENSITY","value":"Energy intensity level of final energy (MJ\/2011 USD PPP)"},"country":{"id":"HK","value":"Hong Kong SAR, China"},"value":"1.06386760588606","decimal":"2","date":"2006"},{"indicator":{"id":"8.1.2_FINAL.ENERGY.INTENSITY","value":"Energy intensity level of final energy (MJ\/2011 USD PPP)"},"country":{"id":"HK","value":"Hong Kong SAR, China"},"value":"1.10769436621482","decimal":"2","date":"2005"},{"indicator":{"id":"8.1.2_FINAL.ENERGY.INTENSITY","value":"Energy intensity level of final energy (MJ\/2011 USD PPP)"},"country":{"id":"HK","value":"Hong Kong SAR, China"},"value":"1.2095830762703","decimal":"2","date":"2004"},{"indicator":{"id":"8.1.2_FINAL.ENERGY.INTENSITY","value":"Energy intensity level of final energy (MJ\/2011 USD PPP)"},"country":{"id":"HK","value":"Hong Kong SAR, China"},"value":"1.41150054375108","decimal":"2","date":"2003"},{"indicator":{"id":"8.1.2_FINAL.ENERGY.INTENSITY","value":"Energy intensity level of final energy (MJ\/2011 USD PPP)"},"country":{"id":"HK","value":"Hong Kong SAR, China"},"value":"1.48371748216359","decimal":"2","date":"2002"},{"indicator":{"id":"8.1.2_FINAL.ENERGY.INTENSITY","value":"Energy intensity level of final energy (MJ\/2011 USD PPP)"},"country":{"id":"HK","value":"Hong Kong SAR, China"},"value":"1.6618495681489","decimal":"2","date":"2001"},{"indicator":{"id":"8.1.2_FINAL.ENERGY.INTENSITY","value":"Energy intensity level of final energy (MJ\/2011 USD PPP)"},"country":{"id":"HK","value":"Hong Kong SAR, China"},"value":"1.67425619296006","decimal":"2","date":"2000"},{"indicator":{"id":"8.1.2_FINAL.ENERGY.INTENSITY","value":"Energy intensity level of final energy (MJ\/2011 USD PPP)"},"country":{"id":"HK","value":"Hong Kong SAR, China"},"value":"2.11829382168368","decimal":"2","date":"1999"},{"indicator":{"id":"8.1.2_FINAL.ENERGY.INTENSITY","value":"Energy intensity level of final energy (MJ\/2011 USD PPP)"},"country":{"id":"HK","value":"Hong Kong SAR, China"},"value":"1.82775601585777","decimal":"2","date":"1998"},{"indicator":{"id":"8.1.2_FINAL.ENERGY.INTENSITY","value":"Energy intensity level of final energy (MJ\/2011 USD PPP)"},"country":{"id":"HK","value":"Hong Kong SAR, China"},"value":"1.286151711741","decimal":"2","date":"1997"},{"indicator":{"id":"8.1.2_FINAL.ENERGY.INTENSITY","value":"Energy intensity level of final energy (MJ\/2011 USD PPP)"},"country":{"id":"HK","value":"Hong Kong SAR, China"},"value":"1.33503122110779","decimal":"2","date":"1996"},{"indicator":{"id":"8.1.2_FINAL.ENERGY.INTENSITY","value":"Energy intensity level of final energy (MJ\/2011 USD PPP)"},"country":{"id":"HK","value":"Hong Kong SAR, China"},"value":"1.41094090068823","decimal":"2","date":"1995"},{"indicator":{"id":"8.1.2_FINAL.ENERGY.INTENSITY","value":"Energy intensity level of final energy (MJ\/2011 USD PPP)"},"country":{"id":"HK","value":"Hong Kong SAR, China"},"value":"1.47747348768997","decimal":"2","date":"1994"},{"indicator":{"id":"8.1.2_FINAL.ENERGY.INTENSITY","value":"Energy intensity level of final energy (MJ\/2011 USD PPP)"},"country":{"id":"HK","value":"Hong Kong SAR, China"},"value":"1.44227639552024","decimal":"2","date":"1993"},{"indicator":{"id":"8.1.2_FINAL.ENERGY.INTENSITY","value":"Energy intensity level of final energy (MJ\/2011 USD PPP)"},"country":{"id":"HK","value":"Hong Kong SAR, China"},"value":"1.49009979543528","decimal":"2","date":"1992"},{"indicator":{"id":"8.1.2_FINAL.ENERGY.INTENSITY","value":"Energy intensity level of final energy (MJ\/2011 USD PPP)"},"country":{"id":"HK","value":"Hong Kong SAR, China"},"value":"1.36302835274662","decimal":"2","date":"1991"},{"indicator":{"id":"8.1.2_FINAL.ENERGY.INTENSITY","value":"Energy intensity level of final energy (MJ\/2011 USD PPP)"},"country":{"id":"HK","value":"Hong Kong SAR, China"},"value":"1.37862732407054","decimal":"2","date":"1990"}]]