[{"page":1,"pages":1,"per_page":"10000","total":27},[{"indicator":{"id":"3.1.4_BIOFUELS.CONSUM","value":"Liquid biofuels consumption (TJ)"},"country":{"id":"IT","value":"Italy"},"value":null,"decimal":"0","date":"Period 2010-2012"},{"indicator":{"id":"3.1.4_BIOFUELS.CONSUM","value":"Liquid biofuels consumption (TJ)"},"country":{"id":"IT","value":"Italy"},"value":null,"decimal":"0","date":"Period 2000-2010"},{"indicator":{"id":"3.1.4_BIOFUELS.CONSUM","value":"Liquid biofuels consumption (TJ)"},"country":{"id":"IT","value":"Italy"},"value":null,"decimal":"0","date":"Period 1990-2012"},{"indicator":{"id":"3.1.4_BIOFUELS.CONSUM","value":"Liquid biofuels consumption (TJ)"},"country":{"id":"IT","value":"Italy"},"value":null,"decimal":"0","date":"Period 1990-2000"},{"indicator":{"id":"3.1.4_BIOFUELS.CONSUM","value":"Liquid biofuels consumption (TJ)"},"country":{"id":"IT","value":"Italy"},"value":"69125.8965962936","decimal":"0","date":"2012"},{"indicator":{"id":"3.1.4_BIOFUELS.CONSUM","value":"Liquid biofuels consumption (TJ)"},"country":{"id":"IT","value":"Italy"},"value":"68963.6904267311","decimal":"0","date":"2011"},{"indicator":{"id":"3.1.4_BIOFUELS.CONSUM","value":"Liquid biofuels consumption (TJ)"},"country":{"id":"IT","value":"Italy"},"value":"71233.8728932268","decimal":"0","date":"2010"},{"indicator":{"id":"3.1.4_BIOFUELS.CONSUM","value":"Liquid biofuels consumption (TJ)"},"country":{"id":"IT","value":"Italy"},"value":"54001.5753769167","decimal":"0","date":"2009"},{"indicator":{"id":"3.1.4_BIOFUELS.CONSUM","value":"Liquid biofuels consumption (TJ)"},"country":{"id":"IT","value":"Italy"},"value":"30858.8683540038","decimal":"0","date":"2008"},{"indicator":{"id":"3.1.4_BIOFUELS.CONSUM","value":"Liquid biofuels consumption (TJ)"},"country":{"id":"IT","value":"Italy"},"value":"7473.98","decimal":"0","date":"2007"},{"indicator":{"id":"3.1.4_BIOFUELS.CONSUM","value":"Liquid biofuels consumption (TJ)"},"country":{"id":"IT","value":"Italy"},"value":"8251.01","decimal":"0","date":"2006"},{"indicator":{"id":"3.1.4_BIOFUELS.CONSUM","value":"Liquid biofuels consumption (TJ)"},"country":{"id":"IT","value":"Italy"},"value":"7400","decimal":"0","date":"2005"},{"indicator":{"id":"3.1.4_BIOFUELS.CONSUM","value":"Liquid biofuels consumption (TJ)"},"country":{"id":"IT","value":"Italy"},"value":"10582.01","decimal":"0","date":"2004"},{"indicator":{"id":"3.1.4_BIOFUELS.CONSUM","value":"Liquid biofuels consumption (TJ)"},"country":{"id":"IT","value":"Italy"},"value":"0","decimal":"0","date":"2003"},{"indicator":{"id":"3.1.4_BIOFUELS.CONSUM","value":"Liquid biofuels consumption (TJ)"},"country":{"id":"IT","value":"Italy"},"value":"0","decimal":"0","date":"2002"},{"indicator":{"id":"3.1.4_BIOFUELS.CONSUM","value":"Liquid biofuels consumption (TJ)"},"country":{"id":"IT","value":"Italy"},"value":"0","decimal":"0","date":"2001"},{"indicator":{"id":"3.1.4_BIOFUELS.CONSUM","value":"Liquid biofuels consumption (TJ)"},"country":{"id":"IT","value":"Italy"},"value":"0","decimal":"0","date":"2000"},{"indicator":{"id":"3.1.4_BIOFUELS.CONSUM","value":"Liquid biofuels consumption (TJ)"},"country":{"id":"IT","value":"Italy"},"value":"0","decimal":"0","date":"1999"},{"indicator":{"id":"3.1.4_BIOFUELS.CONSUM","value":"Liquid biofuels consumption (TJ)"},"country":{"id":"IT","value":"Italy"},"value":"0","decimal":"0","date":"1998"},{"indicator":{"id":"3.1.4_BIOFUELS.CONSUM","value":"Liquid biofuels consumption (TJ)"},"country":{"id":"IT","value":"Italy"},"value":"0","decimal":"0","date":"1997"},{"indicator":{"id":"3.1.4_BIOFUELS.CONSUM","value":"Liquid biofuels consumption (TJ)"},"country":{"id":"IT","value":"Italy"},"value":"0","decimal":"0","date":"1996"},{"indicator":{"id":"3.1.4_BIOFUELS.CONSUM","value":"Liquid biofuels consumption (TJ)"},"country":{"id":"IT","value":"Italy"},"value":"0","decimal":"0","date":"1995"},{"indicator":{"id":"3.1.4_BIOFUELS.CONSUM","value":"Liquid biofuels consumption (TJ)"},"country":{"id":"IT","value":"Italy"},"value":"0","decimal":"0","date":"1994"},{"indicator":{"id":"3.1.4_BIOFUELS.CONSUM","value":"Liquid biofuels consumption (TJ)"},"country":{"id":"IT","value":"Italy"},"value":"0","decimal":"0","date":"1993"},{"indicator":{"id":"3.1.4_BIOFUELS.CONSUM","value":"Liquid biofuels consumption (TJ)"},"country":{"id":"IT","value":"Italy"},"value":"0","decimal":"0","date":"1992"},{"indicator":{"id":"3.1.4_BIOFUELS.CONSUM","value":"Liquid biofuels consumption (TJ)"},"country":{"id":"IT","value":"Italy"},"value":"0","decimal":"0","date":"1991"},{"indicator":{"id":"3.1.4_BIOFUELS.CONSUM","value":"Liquid biofuels consumption (TJ)"},"country":{"id":"IT","value":"Italy"},"value":"0","decimal":"0","date":"1990"}]]