[{"page":1,"pages":1,"per_page":"10000","total":27},[{"indicator":{"id":"3.1_RE.CONSUMPTION","value":"Renewable energy consumption (TJ)"},"country":{"id":"NP","value":"Nepal"},"value":null,"decimal":"0","date":"Period 2010-2012"},{"indicator":{"id":"3.1_RE.CONSUMPTION","value":"Renewable energy consumption (TJ)"},"country":{"id":"NP","value":"Nepal"},"value":null,"decimal":"0","date":"Period 2000-2010"},{"indicator":{"id":"3.1_RE.CONSUMPTION","value":"Renewable energy consumption (TJ)"},"country":{"id":"NP","value":"Nepal"},"value":null,"decimal":"0","date":"Period 1990-2012"},{"indicator":{"id":"3.1_RE.CONSUMPTION","value":"Renewable energy consumption (TJ)"},"country":{"id":"NP","value":"Nepal"},"value":null,"decimal":"0","date":"Period 1990-2000"},{"indicator":{"id":"3.1_RE.CONSUMPTION","value":"Renewable energy consumption (TJ)"},"country":{"id":"NP","value":"Nepal"},"value":"354238.216875","decimal":"0","date":"2012"},{"indicator":{"id":"3.1_RE.CONSUMPTION","value":"Renewable energy consumption (TJ)"},"country":{"id":"NP","value":"Nepal"},"value":"380337.419158076","decimal":"0","date":"2011"},{"indicator":{"id":"3.1_RE.CONSUMPTION","value":"Renewable energy consumption (TJ)"},"country":{"id":"NP","value":"Nepal"},"value":"368994.893896509","decimal":"0","date":"2010"},{"indicator":{"id":"3.1_RE.CONSUMPTION","value":"Renewable energy consumption (TJ)"},"country":{"id":"NP","value":"Nepal"},"value":"364858.286266453","decimal":"0","date":"2009"},{"indicator":{"id":"3.1_RE.CONSUMPTION","value":"Renewable energy consumption (TJ)"},"country":{"id":"NP","value":"Nepal"},"value":"359566.316081081","decimal":"0","date":"2008"},{"indicator":{"id":"3.1_RE.CONSUMPTION","value":"Renewable energy consumption (TJ)"},"country":{"id":"NP","value":"Nepal"},"value":"352430.393567335","decimal":"0","date":"2007"},{"indicator":{"id":"3.1_RE.CONSUMPTION","value":"Renewable energy consumption (TJ)"},"country":{"id":"NP","value":"Nepal"},"value":"344938.880673217","decimal":"0","date":"2006"},{"indicator":{"id":"3.1_RE.CONSUMPTION","value":"Renewable energy consumption (TJ)"},"country":{"id":"NP","value":"Nepal"},"value":"338400.495602053","decimal":"0","date":"2005"},{"indicator":{"id":"3.1_RE.CONSUMPTION","value":"Renewable energy consumption (TJ)"},"country":{"id":"NP","value":"Nepal"},"value":"330933.686170389","decimal":"0","date":"2004"},{"indicator":{"id":"3.1_RE.CONSUMPTION","value":"Renewable energy consumption (TJ)"},"country":{"id":"NP","value":"Nepal"},"value":"323323.321892369","decimal":"0","date":"2003"},{"indicator":{"id":"3.1_RE.CONSUMPTION","value":"Renewable energy consumption (TJ)"},"country":{"id":"NP","value":"Nepal"},"value":"315976.683235987","decimal":"0","date":"2002"},{"indicator":{"id":"3.1_RE.CONSUMPTION","value":"Renewable energy consumption (TJ)"},"country":{"id":"NP","value":"Nepal"},"value":"304942.79891805","decimal":"0","date":"2001"},{"indicator":{"id":"3.1_RE.CONSUMPTION","value":"Renewable energy consumption (TJ)"},"country":{"id":"NP","value":"Nepal"},"value":"296792.158553345","decimal":"0","date":"2000"},{"indicator":{"id":"3.1_RE.CONSUMPTION","value":"Renewable energy consumption (TJ)"},"country":{"id":"NP","value":"Nepal"},"value":"279832.44717862","decimal":"0","date":"1999"},{"indicator":{"id":"3.1_RE.CONSUMPTION","value":"Renewable energy consumption (TJ)"},"country":{"id":"NP","value":"Nepal"},"value":"273283.700224","decimal":"0","date":"1998"},{"indicator":{"id":"3.1_RE.CONSUMPTION","value":"Renewable energy consumption (TJ)"},"country":{"id":"NP","value":"Nepal"},"value":"267281.624140291","decimal":"0","date":"1997"},{"indicator":{"id":"3.1_RE.CONSUMPTION","value":"Renewable energy consumption (TJ)"},"country":{"id":"NP","value":"Nepal"},"value":"261563.983251433","decimal":"0","date":"1996"},{"indicator":{"id":"3.1_RE.CONSUMPTION","value":"Renewable energy consumption (TJ)"},"country":{"id":"NP","value":"Nepal"},"value":"255819.239205686","decimal":"0","date":"1995"},{"indicator":{"id":"3.1_RE.CONSUMPTION","value":"Renewable energy consumption (TJ)"},"country":{"id":"NP","value":"Nepal"},"value":"250040.448504951","decimal":"0","date":"1994"},{"indicator":{"id":"3.1_RE.CONSUMPTION","value":"Renewable energy consumption (TJ)"},"country":{"id":"NP","value":"Nepal"},"value":"244530.418113612","decimal":"0","date":"1993"},{"indicator":{"id":"3.1_RE.CONSUMPTION","value":"Renewable energy consumption (TJ)"},"country":{"id":"NP","value":"Nepal"},"value":"239342.52782167","decimal":"0","date":"1992"},{"indicator":{"id":"3.1_RE.CONSUMPTION","value":"Renewable energy consumption (TJ)"},"country":{"id":"NP","value":"Nepal"},"value":"234348.30304721","decimal":"0","date":"1991"},{"indicator":{"id":"3.1_RE.CONSUMPTION","value":"Renewable energy consumption (TJ)"},"country":{"id":"NP","value":"Nepal"},"value":"229285.694031891","decimal":"0","date":"1990"}]]