[{"page":1,"pages":1,"per_page":"10000","total":27},[{"indicator":{"id":"8.1.1_FINAL.ENERGY.CONSUMPTION","value":"Total final consumption (TJ)"},"country":{"id":"SE","value":"Sweden"},"value":null,"decimal":"0","date":"Period 2010-2012"},{"indicator":{"id":"8.1.1_FINAL.ENERGY.CONSUMPTION","value":"Total final consumption (TJ)"},"country":{"id":"SE","value":"Sweden"},"value":null,"decimal":"0","date":"Period 2000-2010"},{"indicator":{"id":"8.1.1_FINAL.ENERGY.CONSUMPTION","value":"Total final consumption (TJ)"},"country":{"id":"SE","value":"Sweden"},"value":null,"decimal":"0","date":"Period 1990-2012"},{"indicator":{"id":"8.1.1_FINAL.ENERGY.CONSUMPTION","value":"Total final consumption (TJ)"},"country":{"id":"SE","value":"Sweden"},"value":null,"decimal":"0","date":"Period 1990-2000"},{"indicator":{"id":"8.1.1_FINAL.ENERGY.CONSUMPTION","value":"Total final consumption (TJ)"},"country":{"id":"SE","value":"Sweden"},"value":"1302991.73","decimal":"0","date":"2012"},{"indicator":{"id":"8.1.1_FINAL.ENERGY.CONSUMPTION","value":"Total final consumption (TJ)"},"country":{"id":"SE","value":"Sweden"},"value":"1301763.96","decimal":"0","date":"2011"},{"indicator":{"id":"8.1.1_FINAL.ENERGY.CONSUMPTION","value":"Total final consumption (TJ)"},"country":{"id":"SE","value":"Sweden"},"value":"1371243.99","decimal":"0","date":"2010"},{"indicator":{"id":"8.1.1_FINAL.ENERGY.CONSUMPTION","value":"Total final consumption (TJ)"},"country":{"id":"SE","value":"Sweden"},"value":"1266641.85","decimal":"0","date":"2009"},{"indicator":{"id":"8.1.1_FINAL.ENERGY.CONSUMPTION","value":"Total final consumption (TJ)"},"country":{"id":"SE","value":"Sweden"},"value":"1294681.57","decimal":"0","date":"2008"},{"indicator":{"id":"8.1.1_FINAL.ENERGY.CONSUMPTION","value":"Total final consumption (TJ)"},"country":{"id":"SE","value":"Sweden"},"value":"1338654.9","decimal":"0","date":"2007"},{"indicator":{"id":"8.1.1_FINAL.ENERGY.CONSUMPTION","value":"Total final consumption (TJ)"},"country":{"id":"SE","value":"Sweden"},"value":"1333078.5","decimal":"0","date":"2006"},{"indicator":{"id":"8.1.1_FINAL.ENERGY.CONSUMPTION","value":"Total final consumption (TJ)"},"country":{"id":"SE","value":"Sweden"},"value":"1350116.06","decimal":"0","date":"2005"},{"indicator":{"id":"8.1.1_FINAL.ENERGY.CONSUMPTION","value":"Total final consumption (TJ)"},"country":{"id":"SE","value":"Sweden"},"value":"1362955.76","decimal":"0","date":"2004"},{"indicator":{"id":"8.1.1_FINAL.ENERGY.CONSUMPTION","value":"Total final consumption (TJ)"},"country":{"id":"SE","value":"Sweden"},"value":"1372073.18","decimal":"0","date":"2003"},{"indicator":{"id":"8.1.1_FINAL.ENERGY.CONSUMPTION","value":"Total final consumption (TJ)"},"country":{"id":"SE","value":"Sweden"},"value":"1379102.02","decimal":"0","date":"2002"},{"indicator":{"id":"8.1.1_FINAL.ENERGY.CONSUMPTION","value":"Total final consumption (TJ)"},"country":{"id":"SE","value":"Sweden"},"value":"1379686.29","decimal":"0","date":"2001"},{"indicator":{"id":"8.1.1_FINAL.ENERGY.CONSUMPTION","value":"Total final consumption (TJ)"},"country":{"id":"SE","value":"Sweden"},"value":"1405377.33","decimal":"0","date":"2000"},{"indicator":{"id":"8.1.1_FINAL.ENERGY.CONSUMPTION","value":"Total final consumption (TJ)"},"country":{"id":"SE","value":"Sweden"},"value":"1414275","decimal":"0","date":"1999"},{"indicator":{"id":"8.1.1_FINAL.ENERGY.CONSUMPTION","value":"Total final consumption (TJ)"},"country":{"id":"SE","value":"Sweden"},"value":"1434616.31","decimal":"0","date":"1998"},{"indicator":{"id":"8.1.1_FINAL.ENERGY.CONSUMPTION","value":"Total final consumption (TJ)"},"country":{"id":"SE","value":"Sweden"},"value":"1422155.56","decimal":"0","date":"1997"},{"indicator":{"id":"8.1.1_FINAL.ENERGY.CONSUMPTION","value":"Total final consumption (TJ)"},"country":{"id":"SE","value":"Sweden"},"value":"1455116.35","decimal":"0","date":"1996"},{"indicator":{"id":"8.1.1_FINAL.ENERGY.CONSUMPTION","value":"Total final consumption (TJ)"},"country":{"id":"SE","value":"Sweden"},"value":"1415832.2","decimal":"0","date":"1995"},{"indicator":{"id":"8.1.1_FINAL.ENERGY.CONSUMPTION","value":"Total final consumption (TJ)"},"country":{"id":"SE","value":"Sweden"},"value":"1383134","decimal":"0","date":"1994"},{"indicator":{"id":"8.1.1_FINAL.ENERGY.CONSUMPTION","value":"Total final consumption (TJ)"},"country":{"id":"SE","value":"Sweden"},"value":"1360605.29","decimal":"0","date":"1993"},{"indicator":{"id":"8.1.1_FINAL.ENERGY.CONSUMPTION","value":"Total final consumption (TJ)"},"country":{"id":"SE","value":"Sweden"},"value":"1349919.44","decimal":"0","date":"1992"},{"indicator":{"id":"8.1.1_FINAL.ENERGY.CONSUMPTION","value":"Total final consumption (TJ)"},"country":{"id":"SE","value":"Sweden"},"value":"1275600.47","decimal":"0","date":"1991"},{"indicator":{"id":"8.1.1_FINAL.ENERGY.CONSUMPTION","value":"Total final consumption (TJ)"},"country":{"id":"SE","value":"Sweden"},"value":"1263833.9","decimal":"0","date":"1990"}]]