[{"page":1,"pages":1,"per_page":"10000","total":27},[{"indicator":{"id":"3.1.6_SOLAR.CONSUM","value":"Solar energy consumption (TJ)"},"country":{"id":"XD","value":"High income"},"value":null,"decimal":"0","date":"Period 2010-2012"},{"indicator":{"id":"3.1.6_SOLAR.CONSUM","value":"Solar energy consumption (TJ)"},"country":{"id":"XD","value":"High income"},"value":null,"decimal":"0","date":"Period 2000-2010"},{"indicator":{"id":"3.1.6_SOLAR.CONSUM","value":"Solar energy consumption (TJ)"},"country":{"id":"XD","value":"High income"},"value":null,"decimal":"0","date":"Period 1990-2012"},{"indicator":{"id":"3.1.6_SOLAR.CONSUM","value":"Solar energy consumption (TJ)"},"country":{"id":"XD","value":"High income"},"value":null,"decimal":"0","date":"Period 1990-2000"},{"indicator":{"id":"3.1.6_SOLAR.CONSUM","value":"Solar energy consumption (TJ)"},"country":{"id":"XD","value":"High income"},"value":"501556.394635167","decimal":"0","date":"2012"},{"indicator":{"id":"3.1.6_SOLAR.CONSUM","value":"Solar energy consumption (TJ)"},"country":{"id":"XD","value":"High income"},"value":"399809.585446376","decimal":"0","date":"2011"},{"indicator":{"id":"3.1.6_SOLAR.CONSUM","value":"Solar energy consumption (TJ)"},"country":{"id":"XD","value":"High income"},"value":"298928.351365489","decimal":"0","date":"2010"},{"indicator":{"id":"3.1.6_SOLAR.CONSUM","value":"Solar energy consumption (TJ)"},"country":{"id":"XD","value":"High income"},"value":"248190.606001297","decimal":"0","date":"2009"},{"indicator":{"id":"3.1.6_SOLAR.CONSUM","value":"Solar energy consumption (TJ)"},"country":{"id":"XD","value":"High income"},"value":"215718.693361403","decimal":"0","date":"2008"},{"indicator":{"id":"3.1.6_SOLAR.CONSUM","value":"Solar energy consumption (TJ)"},"country":{"id":"XD","value":"High income"},"value":"181008.795677251","decimal":"0","date":"2007"},{"indicator":{"id":"3.1.6_SOLAR.CONSUM","value":"Solar energy consumption (TJ)"},"country":{"id":"XD","value":"High income"},"value":"163158.561754839","decimal":"0","date":"2006"},{"indicator":{"id":"3.1.6_SOLAR.CONSUM","value":"Solar energy consumption (TJ)"},"country":{"id":"XD","value":"High income"},"value":"153290.144294551","decimal":"0","date":"2005"},{"indicator":{"id":"3.1.6_SOLAR.CONSUM","value":"Solar energy consumption (TJ)"},"country":{"id":"XD","value":"High income"},"value":"148239.948701527","decimal":"0","date":"2004"},{"indicator":{"id":"3.1.6_SOLAR.CONSUM","value":"Solar energy consumption (TJ)"},"country":{"id":"XD","value":"High income"},"value":"145235.96530514","decimal":"0","date":"2003"},{"indicator":{"id":"3.1.6_SOLAR.CONSUM","value":"Solar energy consumption (TJ)"},"country":{"id":"XD","value":"High income"},"value":"147061.815554648","decimal":"0","date":"2002"},{"indicator":{"id":"3.1.6_SOLAR.CONSUM","value":"Solar energy consumption (TJ)"},"country":{"id":"XD","value":"High income"},"value":"144526.083205449","decimal":"0","date":"2001"},{"indicator":{"id":"3.1.6_SOLAR.CONSUM","value":"Solar energy consumption (TJ)"},"country":{"id":"XD","value":"High income"},"value":"146324.725040304","decimal":"0","date":"2000"},{"indicator":{"id":"3.1.6_SOLAR.CONSUM","value":"Solar energy consumption (TJ)"},"country":{"id":"XD","value":"High income"},"value":"143178.010558868","decimal":"0","date":"1999"},{"indicator":{"id":"3.1.6_SOLAR.CONSUM","value":"Solar energy consumption (TJ)"},"country":{"id":"XD","value":"High income"},"value":"81822.4229440683","decimal":"0","date":"1998"},{"indicator":{"id":"3.1.6_SOLAR.CONSUM","value":"Solar energy consumption (TJ)"},"country":{"id":"XD","value":"High income"},"value":"84090.003449689","decimal":"0","date":"1997"},{"indicator":{"id":"3.1.6_SOLAR.CONSUM","value":"Solar energy consumption (TJ)"},"country":{"id":"XD","value":"High income"},"value":"81276.8058499373","decimal":"0","date":"1996"},{"indicator":{"id":"3.1.6_SOLAR.CONSUM","value":"Solar energy consumption (TJ)"},"country":{"id":"XD","value":"High income"},"value":"80569.1383579928","decimal":"0","date":"1995"},{"indicator":{"id":"3.1.6_SOLAR.CONSUM","value":"Solar energy consumption (TJ)"},"country":{"id":"XD","value":"High income"},"value":"78301.3102204617","decimal":"0","date":"1994"},{"indicator":{"id":"3.1.6_SOLAR.CONSUM","value":"Solar energy consumption (TJ)"},"country":{"id":"XD","value":"High income"},"value":"76471.4374201879","decimal":"0","date":"1993"},{"indicator":{"id":"3.1.6_SOLAR.CONSUM","value":"Solar energy consumption (TJ)"},"country":{"id":"XD","value":"High income"},"value":"75468.4110808047","decimal":"0","date":"1992"},{"indicator":{"id":"3.1.6_SOLAR.CONSUM","value":"Solar energy consumption (TJ)"},"country":{"id":"XD","value":"High income"},"value":"76009.6901239294","decimal":"0","date":"1991"},{"indicator":{"id":"3.1.6_SOLAR.CONSUM","value":"Solar energy consumption (TJ)"},"country":{"id":"XD","value":"High income"},"value":"75548.4120008158","decimal":"0","date":"1990"}]]